auraboros/__init__.py
auraboros/__main__.py
auraboros/animation.py
auraboros/core.py
auraboros/default.frag
auraboros/default.vert
auraboros/designpattern.py
auraboros/engine.py
auraboros/gamecamera.py
auraboros/gameinput.py
auraboros/gamescene.py
auraboros/gametext.py
auraboros/getasset_order.json
auraboros/particle.py
auraboros/schedule.py
auraboros/shader.py
auraboros/ui.py
auraboros/__pyinstaller/__init__.py
auraboros/__pyinstaller/hook-auraboros.py
auraboros/__pyinstaller/test_auraboros_packaging.py
auraboros/ecs/__init__.py
auraboros/ecs/common.py
auraboros/ecs/world.py
auraboros/examples/__init__.py
auraboros/examples/helloworld.py
auraboros/examples/setup_syspath.py
auraboros/examples/shooting_game.py
auraboros/examples/ui_showcase.py
auraboros/examples/assets/fonts/misaki_gothic.ttf
auraboros/examples/assets/fonts/PixelMplus/PixelMplus10-Regular.ttf
auraboros/examples/assets/fonts/PixelMplus/PixelMplus12-Regular.ttf
auraboros/examples/assets/fonts/PixelMplus/README.txt
auraboros/examples/assets/fonts/PixelMplus/mplus_bitmap_fonts/LICENSE_E
auraboros/examples/assets/fonts/PixelMplus/mplus_bitmap_fonts/LICENSE_J
auraboros/examples/assets/fonts/PixelMplus/mplus_bitmap_fonts/README_E
auraboros/examples/assets/fonts/PixelMplus/mplus_bitmap_fonts/README_J
auraboros/examples/assets/imgs/testsprite.png
auraboros/examples/deprecated/animate_msgbox.py
auraboros/examples/deprecated/animation.py
auraboros/examples/deprecated/animationimage.py
auraboros/examples/deprecated/entity.py
auraboros/examples/deprecated/gametext.py
auraboros/examples/deprecated/helloworld.py
auraboros/examples/deprecated/keyboard.py
auraboros/examples/deprecated/keyframe_animation.py
auraboros/examples/deprecated/menu_ui.py
auraboros/examples/deprecated/mouse.py
auraboros/examples/deprecated/msgbox.py
auraboros/examples/deprecated/particle.py
auraboros/examples/deprecated/scene_transition.py
auraboros/examples/deprecated/schedule.py
auraboros/examples/deprecated/shader.py
auraboros-2.2.0a0.dist-info/METADATA
auraboros-2.2.0a0.dist-info/WHEEL
auraboros-2.2.0a0.dist-info/entry_points.txt
auraboros-2.2.0a0.dist-info/licenses/LICENSE
auraboros-2.2.0a0.dist-info/RECORD
