Metadata-Version: 2.1
Name: auraboros
Version: 2.2.0a0
License-File: LICENSE
Requires-Python: >=3.11.1
Requires-Dist: moderngl
Requires-Dist: pygame
Provides-Extra: dev
Requires-Dist: click; extra == 'dev'
